mcphub/__init__.py
mcphub/mcphub.py
mcphub/adapters/autogen.py
mcphub/adapters/base.py
mcphub/adapters/langchain.py
mcphub/adapters/openai.py
mcphub/cli/README.md
mcphub/cli/__init__.py
mcphub/cli/commands.py
mcphub/cli/process_manager.py
mcphub/cli/utils.py
mcphub/mcp_servers/__init__.py
mcphub/mcp_servers/exceptions.py
mcphub/mcp_servers/params.py
mcphub/mcp_servers/schemas.py
mcphub/mcp_servers/servers.py
mcphub-0.1.11.dist-info/METADATA
mcphub-0.1.11.dist-info/WHEEL
mcphub-0.1.11.dist-info/entry_points.txt
mcphub-0.1.11.dist-info/RECORD
