Metadata-Version: 2.4
Name: mcphub
Version: 0.1.11
Summary: A Python package for managing and integrating Model Context Protocol (MCP) servers with AI frameworks like OpenAI Agents, LangChain, and Autogen
Project-URL: Documentation, https://raw.githubusercontent.com/Cognitive-Stack/mcphub/refs/heads/master/README.md
Project-URL: Issues, https://github.com/Cognitive-Stack/mcphub/issues
Project-URL: Source, https://github.com/Cognitive-Stack/mcphub
Author-email: Hieu TRAN <hieutrantrung.it@gmail.com>, Thang LE <levietthang0512@outlook.com>
License: MIT
Classifier: Development Status :: 3 - Alpha
Classifier: Intended Audience :: Developers
Classifier: License :: OSI Approved :: MIT License
Classifier: Programming Language :: Python :: 3
Classifier: Programming Language :: Python :: 3.10
Classifier: Programming Language :: Python :: 3.11
Classifier: Programming Language :: Python :: 3.12
Requires-Python: <4.0,>=3.10
Requires-Dist: openai<2.0.0,>=1.78.0
Requires-Dist: psutil<8.0.0,>=7.0.0
Requires-Dist: pydantic<3.0.0,>=2.11.4
Requires-Dist: rich<15.0.0,>=14.0.0
Provides-Extra: all
Requires-Dist: autogen-ext[mcp]<0.6.0,>=0.5.1; extra == 'all'
Requires-Dist: langchain-mcp-adapters<0.0.8,>=0.0.7; extra == 'all'
Requires-Dist: openai-agents<0.0.10,>=0.0.9; extra == 'all'
Provides-Extra: autogen
Requires-Dist: autogen-ext[mcp]<0.6.0,>=0.5.1; extra == 'autogen'
Provides-Extra: dev
Requires-Dist: build<2.0.0,>=1.2.2.post1; extra == 'dev'
Requires-Dist: twine<7.0.0,>=6.1.0; extra == 'dev'
Provides-Extra: langchain
Requires-Dist: langchain-mcp-adapters<0.0.8,>=0.0.7; extra == 'langchain'
Provides-Extra: openai
Requires-Dist: openai-agents<0.0.10,>=0.0.9; extra == 'openai'
